examon_pcap_package/__init__.py
examon_pcap_package/questions.py
examon_pcap_package-0.0.1.dist-info/METADATA
examon_pcap_package-0.0.1.dist-info/WHEEL
examon_pcap_package-0.0.1.dist-info/RECORD
